{
  "$schema": "https://developer.microsoft.com/json-schemas/fabric/item/report/definition/visualContainer/2.7.0/schema.json",
  "name": "8356eec789ad132a2c0b",
  "position": {
    "x": 401.7021276595745,
    "y": 0,
    "z": 2000,
    "height": 63.221884498480243,
    "width": 698.35866261398178,
    "tabOrder": 1000
  },
  "visual": {
    "visualType": "advancedSlicerVisual",
    "query": {
      "queryState": {
        "Values": {
          "projections": [
            {
              "field": {
                "Column": {
                  "Expression": {
                    "SourceRef": {
                      "Entity": "Order Line Summary"
                    }
                  },
                  "Property": "Client Name"
                }
              },
              "queryRef": "Order Line Summary.Client Name",
              "nativeQueryRef": "Client Name"
            }
          ]
        }
      }
    },
    "objects": {
      "selection": [
        {
          "properties": {
            "selectAllCheckboxEnabled": {
              "expr": {
                "Literal": {
                  "Value": "true"
                }
              }
            }
          }
        }
      ],
      "general": [
        {
          "properties": {}
        }
      ],
      "data": [
        {
          "properties": {}
        }
      ],
      "layout": [
        {
          "properties": {
            "rowCount": {
              "expr": {
                "Literal": {
                  "Value": "1L"
                }
              }
            },
            "columnCount": {
              "expr": {
                "Literal": {
                  "Value": "6L"
                }
              }
            }
          }
        }
      ]
    },
    "visualContainerObjects": {
      "title": [
        {
          "properties": {
            "show": {
              "expr": {
                "Literal": {
                  "Value": "false"
                }
              }
            }
          }
        }
      ],
      "visualHeader": [
        {
          "properties": {
            "background": {
              "solid": {
                "color": {
                  "expr": {
                    "ThemeDataColor": {
                      "ColorId": 2,
                      "Percent": 0
                    }
                  }
                }
              }
            },
            "show": {
              "expr": {
                "Literal": {
                  "Value": "false"
                }
              }
            }
          }
        }
      ]
    },
    "drillFilterOtherVisuals": true
  },
  "filterConfig": {
    "filters": [
      {
        "name": "290e0ff508d660150041",
        "field": {
          "Column": {
            "Expression": {
              "SourceRef": {
                "Entity": "Order Line Summary"
              }
            },
            "Property": "Client Name"
          }
        },
        "type": "Categorical"
      }
    ]
  }
}