{
  "$schema": "https://developer.microsoft.com/json-schemas/fabric/item/report/definition/visualContainer/2.7.0/schema.json",
  "name": "a3069fc105a50e73e600",
  "position": {
    "x": 436.79214402618658,
    "y": 75.417348608837969,
    "z": 2002,
    "height": 246.15384615384616,
    "width": 843.20785597381337,
    "tabOrder": 2002
  },
  "visual": {
    "visualType": "pivotTable",
    "query": {
      "queryState": {
        "Columns": {
          "projections": [
            {
              "field": {
                "Column": {
                  "Expression": {
                    "SourceRef": {
                      "Entity": "Order Line Summary"
                    }
                  },
                  "Property": "Line Range"
                }
              },
              "queryRef": "Order Line Summary.Line Range",
              "nativeQueryRef": "Line Range",
              "active": true
            }
          ]
        },
        "Rows": {
          "projections": [
            {
              "field": {
                "Column": {
                  "Expression": {
                    "SourceRef": {
                      "Entity": "Order Line Summary"
                    }
                  },
                  "Property": "Client Name"
                }
              },
              "queryRef": "Order Line Summary.Client Name",
              "nativeQueryRef": "Client Name",
              "active": true
            }
          ]
        },
        "Values": {
          "projections": [
            {
              "field": {
                "Aggregation": {
                  "Expression": {
                    "Column": {
                      "Expression": {
                        "SourceRef": {
                          "Entity": "Order Line Summary"
                        }
                      },
                      "Property": "ORDNUM"
                    }
                  },
                  "Function": 2
                }
              },
              "queryRef": "Count(Order Line Summary.ORDNUM)",
              "nativeQueryRef": "Orders Count",
              "displayName": "Orders Count",
              "format": "#,0"
            },
            {
              "field": {
                "Arithmetic": {
                  "Left": {
                    "Aggregation": {
                      "Expression": {
                        "Column": {
                          "Expression": {
                            "SourceRef": {
                              "Entity": "Order Line Summary"
                            }
                          },
                          "Property": "ORDNUM"
                        }
                      },
                      "Function": 2
                    }
                  },
                  "Right": {
                    "ScopedEval": {
                      "Expression": {
                        "Aggregation": {
                          "Expression": {
                            "Column": {
                              "Expression": {
                                "SourceRef": {
                                  "Entity": "Order Line Summary"
                                }
                              },
                              "Property": "ORDNUM"
                            }
                          },
                          "Function": 2
                        }
                      },
                      "Scope": [
                        {
                          "RoleRef": {
                            "Role": "Rows"
                          }
                        }
                      ]
                    }
                  },
                  "Operator": 3
                }
              },
              "queryRef": "Divide(Count(Order Line Summary.ORDNUM), ScopedEval(Count(Order Line Summary.ORDNUM), [Role.Rows]))",
              "nativeQueryRef": "Orders Percentage",
              "displayName": "Orders Percentage"
            }
          ]
        }
      },
      "sortDefinition": {
        "sort": [
          {
            "field": {
              "Aggregation": {
                "Expression": {
                  "Column": {
                    "Expression": {
                      "SourceRef": {
                        "Entity": "Order Line Summary"
                      }
                    },
                    "Property": "ORDNUM"
                  }
                },
                "Function": 2
              }
            },
            "direction": "Descending"
          }
        ],
        "isDefaultSort": true
      }
    },
    "objects": {
      "columnWidth": [
        {
          "properties": {
            "value": {
              "expr": {
                "Literal": {
                  "Value": "82.94599018003274D"
                }
              }
            }
          },
          "selector": {
            "data": [
              {
                "scopeId": {
                  "Comparison": {
                    "ComparisonKind": 0,
                    "Left": {
                      "Column": {
                        "Expression": {
                          "SourceRef": {
                            "Entity": "Order Line Summary"
                          }
                        },
                        "Property": "Client Name"
                      }
                    },
                    "Right": {
                      "Literal": {
                        "Value": "'TATA'"
                      }
                    }
                  }
                }
              }
            ]
          }
        }
      ],
      "general": [
        {
          "properties": {
            "layout": {
              "expr": {
                "Literal": {
                  "Value": "'Tabular'"
                }
              }
            }
          }
        }
      ],
      "columnHeaders": [
        {
          "properties": {
            "titleAlignment": {
              "expr": {
                "Literal": {
                  "Value": "'Center'"
                }
              }
            },
            "columnAdjustment": {
              "expr": {
                "Literal": {
                  "Value": "'growToFit'"
                }
              }
            }
          }
        }
      ],
      "columnFormatting": [
        {
          "properties": {
            "alignment": {
              "expr": {
                "Literal": {
                  "Value": "'Center'"
                }
              }
            }
          },
          "selector": {
            "metadata": "Count(Order Line Summary.ORDNUM)"
          }
        },
        {
          "properties": {
            "alignment": {
              "expr": {
                "Literal": {
                  "Value": "'Center'"
                }
              }
            }
          },
          "selector": {
            "metadata": "Divide(Count(Order Line Summary.ORDNUM), ScopedEval(Count(Order Line Summary.ORDNUM), [Role.Rows]))"
          }
        }
      ]
    },
    "visualContainerObjects": {
      "title": [
        {
          "properties": {
            "text": {
              "expr": {
                "Literal": {
                  "Value": "'Orders Split By No Of Lines'"
                }
              }
            }
          }
        }
      ],
      "visualHeader": [
        {
          "properties": {
            "background": {
              "solid": {
                "color": {
                  "expr": {
                    "ThemeDataColor": {
                      "ColorId": 2,
                      "Percent": 0
                    }
                  }
                }
              }
            }
          }
        }
      ]
    },
    "drillFilterOtherVisuals": true
  },
  "filterConfig": {
    "filters": [
      {
        "name": "96599137b15a34ed0707",
        "field": {
          "Aggregation": {
            "Expression": {
              "Column": {
                "Expression": {
                  "SourceRef": {
                    "Entity": "Order Line Summary"
                  }
                },
                "Property": "ORDNUM"
              }
            },
            "Function": 2
          }
        },
        "type": "Advanced"
      },
      {
        "name": "b1652e04776a0b0c6ac8",
        "field": {
          "Arithmetic": {
            "Left": {
              "Aggregation": {
                "Expression": {
                  "Column": {
                    "Expression": {
                      "SourceRef": {
                        "Entity": "Order Line Summary"
                      }
                    },
                    "Property": "ORDNUM"
                  }
                },
                "Function": 2
              }
            },
            "Right": {
              "ScopedEval": {
                "Expression": {
                  "Aggregation": {
                    "Expression": {
                      "Column": {
                        "Expression": {
                          "SourceRef": {
                            "Entity": "Order Line Summary"
                          }
                        },
                        "Property": "ORDNUM"
                      }
                    },
                    "Function": 2
                  }
                },
                "Scope": []
              }
            },
            "Operator": 3
          }
        },
        "type": "Advanced",
        "howCreated": "User"
      },
      {
        "name": "1ecf44118228e27085db",
        "field": {
          "Arithmetic": {
            "Left": {
              "Aggregation": {
                "Expression": {
                  "Column": {
                    "Expression": {
                      "SourceRef": {
                        "Entity": "Order Line Summary"
                      }
                    },
                    "Property": "ORDNUM"
                  }
                },
                "Function": 2
              }
            },
            "Right": {
              "ScopedEval": {
                "Expression": {
                  "Aggregation": {
                    "Expression": {
                      "Column": {
                        "Expression": {
                          "SourceRef": {
                            "Entity": "Order Line Summary"
                          }
                        },
                        "Property": "ORDNUM"
                      }
                    },
                    "Function": 2
                  }
                },
                "Scope": [
                  {
                    "RoleRef": {
                      "Role": "Columns"
                    }
                  }
                ]
              }
            },
            "Operator": 3
          }
        },
        "type": "Advanced",
        "howCreated": "User"
      },
      {
        "name": "f25603de335e82986041",
        "field": {
          "Arithmetic": {
            "Left": {
              "Aggregation": {
                "Expression": {
                  "Column": {
                    "Expression": {
                      "SourceRef": {
                        "Entity": "Order Line Summary"
                      }
                    },
                    "Property": "ORDNUM"
                  }
                },
                "Function": 2
              }
            },
            "Right": {
              "ScopedEval": {
                "Expression": {
                  "Aggregation": {
                    "Expression": {
                      "Column": {
                        "Expression": {
                          "SourceRef": {
                            "Entity": "Order Line Summary"
                          }
                        },
                        "Property": "ORDNUM"
                      }
                    },
                    "Function": 2
                  }
                },
                "Scope": [
                  {
                    "RoleRef": {
                      "Role": "Rows"
                    }
                  }
                ]
              }
            },
            "Operator": 3
          }
        },
        "type": "Advanced"
      },
      {
        "name": "f8e0ee49b8139047b272",
        "field": {
          "Column": {
            "Expression": {
              "SourceRef": {
                "Entity": "Order Line Summary"
              }
            },
            "Property": "Client Name"
          }
        },
        "type": "Categorical"
      },
      {
        "name": "41346a52c9a898760e13",
        "field": {
          "Column": {
            "Expression": {
              "SourceRef": {
                "Entity": "Order Line Summary"
              }
            },
            "Property": "Line Range"
          }
        },
        "type": "Categorical"
      }
    ]
  }
}